Metadata-Version: 2.1
Name: lovelyweblib
Version: 0.0.1
Summary: Get the response of given URLs
Author: 
License-File: licence.txt
